my_package/__init__.py
my_simple_package_2_2_2_2_2-0.1.0.dist-info/licenses/LICENSE
my_simple_package_2_2_2_2_2-0.1.0.dist-info/METADATA
my_simple_package_2_2_2_2_2-0.1.0.dist-info/WHEEL
my_simple_package_2_2_2_2_2-0.1.0.dist-info/top_level.txt
my_simple_package_2_2_2_2_2-0.1.0.dist-info/RECORD
