Metadata-Version: 2.4
Name: my-simple-package-2-2-2-2-2
Version: 0.1.0
Summary: Простой пример пакета
Home-page: https://github.com/yourusername/my-simple-package
Author: Ваше Имя
Author-email: you@example.com
Classifier: Programming Language :: Python :: 3
Classifier: License :: OSI Approved :: MIT License
Requires-Python: >=3.6
License-File: LICENSE
Dynamic: author
Dynamic: author-email
Dynamic: classifier
Dynamic: description
Dynamic: description-content-type
Dynamic: home-page
Dynamic: license-file
Dynamic: requires-python
Dynamic: summary
